plone.api-2.5.3-py3.13-nspkg.pth
plone/api/__init__.py
plone/api/addon.py
plone/api/configure.zcml
plone/api/content.py
plone/api/env.py
plone/api/exc.py
plone/api/group.py
plone/api/portal.py
plone/api/relation.py
plone/api/testing.zcml
plone/api/user.py
plone/api/validation.py
plone/api/profiles/testfixture/metadata.xml
plone/api/profiles/testfixture/types.xml
plone/api/profiles/testfixture/types/Dexterity_Folder.xml
plone/api/profiles/testfixture/types/Dexterity_Item.xml
plone/api/tests/Dexterity_Folder.xml
plone/api/tests/Dexterity_Item.xml
plone/api/tests/__init__.py
plone/api/tests/base.py
plone/api/tests/test_addon.py
plone/api/tests/test_content.py
plone/api/tests/test_doctests.py
plone/api/tests/test_env.py
plone/api/tests/test_group.py
plone/api/tests/test_portal.py
plone/api/tests/test_relation.py
plone/api/tests/test_user.py
plone/api/tests/test_validation.py
plone/api/tests/doctests/about.md
plone/api/tests/doctests/addon.md
plone/api/tests/doctests/content.md
plone/api/tests/doctests/contribute.md
plone/api/tests/doctests/env.md
plone/api/tests/doctests/group.md
plone/api/tests/doctests/portal.md
plone/api/tests/doctests/relation.md
plone/api/tests/doctests/user.md
plone_api-2.5.3.dist-info/LICENSE
plone_api-2.5.3.dist-info/METADATA
plone_api-2.5.3.dist-info/WHEEL
plone_api-2.5.3.dist-info/namespace_packages.txt
plone_api-2.5.3.dist-info/top_level.txt
plone_api-2.5.3.dist-info/RECORD
