Metadata-Version: 2.2
Name: plone.api
Version: 2.5.3
Summary: A Plone API.
Home-page: https://github.com/plone/plone.api
Author: Plone Foundation
Author-email: plone-developers@lists.sourceforge.net
License: GPL version 2
Project-URL: Documentation, https://6.docs.plone.org/plone.api/index.html
Project-URL: Changelog, https://github.com/plone/plone.api/blob/main/CHANGES.md
Project-URL: Issue Tracker, https://github.com/plone/plone.api/issues
Project-URL: Repository, https://github.com/plone/plone.api
Project-URL: Sponsor, https://github.com/sponsors/plone
Project-URL: Discord, https://discord.com/channels/786421998426521600/786421998426521603
Project-URL: Mastodon, https://plone.social/@plone
Project-URL: YouTube, https://www.youtube.com/@plonecms
Keywords: plone api
Platform: Any
Classifier: Development Status :: 5 - Production/Stable
Classifier: Environment :: Web Environment
Classifier: Framework :: Plone
Classifier: Framework :: Plone :: 6.0
Classifier: Framework :: Plone :: Core
Classifier: Intended Audience :: Developers
Classifier: License :: OSI Approved :: GNU General Public License v2 (GPLv2)
Classifier: Operating System :: OS Independent
Classifier: Programming Language :: Python
Classifier: Programming Language :: Python :: 3.8
Classifier: Programming Language :: Python :: 3.9
Classifier: Programming Language :: Python :: 3.10
Classifier: Programming Language :: Python :: 3.11
Requires-Python: >=3.8
License-File: LICENSE
Requires-Dist: Acquisition
Requires-Dist: Products.statusmessages
Requires-Dist: Products.PlonePAS
Requires-Dist: Products.CMFPlone
Requires-Dist: decorator
Requires-Dist: plone.app.uuid
Requires-Dist: plone.app.dexterity
Requires-Dist: plone.app.intid
Requires-Dist: plone.app.linkintegrity
Requires-Dist: plone.base
Requires-Dist: plone.dexterity
Requires-Dist: plone.i18n
Requires-Dist: plone.registry
Requires-Dist: plone.uuid
Requires-Dist: setuptools
Requires-Dist: zope.globalrequest
Requires-Dist: Products.CMFCore
Requires-Dist: z3c.relationfield
Requires-Dist: zc.relation
Requires-Dist: Zope
Requires-Dist: zope.intid
Provides-Extra: test
Requires-Dist: borg.localrole; extra == "test"
Requires-Dist: manuel>=1.11.2; extra == "test"
Requires-Dist: packaging; extra == "test"
Requires-Dist: plone.app.contenttypes; extra == "test"
Requires-Dist: plone.app.textfield; extra == "test"
Requires-Dist: plone.app.testing; extra == "test"
Requires-Dist: plone.testing; extra == "test"
Requires-Dist: plone.indexer; extra == "test"
Requires-Dist: plone.registry; extra == "test"
Dynamic: author
Dynamic: author-email
Dynamic: classifier
Dynamic: description
Dynamic: description-content-type
Dynamic: home-page
Dynamic: keywords
Dynamic: license
Dynamic: platform
Dynamic: project-url
Dynamic: provides-extra
Dynamic: requires-dist
Dynamic: requires-python
Dynamic: summary
